snakemake_executor_plugin_googlebatch/__init__.py
snakemake_executor_plugin_googlebatch/command.py
snakemake_executor_plugin_googlebatch/executor.py
snakemake_executor_plugin_googlebatch/snippet.py
snakemake_executor_plugin_googlebatch/snippets/intel-mpi/include/paths.sh
snakemake_executor_plugin_googlebatch/snippets/intel-mpi/run.sh
snakemake_executor_plugin_googlebatch/snippets/intel-mpi/setup.sh
snakemake_executor_plugin_googlebatch/utils.py
snakemake_executor_plugin_googlebatch-0.5.1.dist-info/METADATA
snakemake_executor_plugin_googlebatch-0.5.1.dist-info/WHEEL
snakemake_executor_plugin_googlebatch-0.5.1.dist-info/licenses/LICENSE
snakemake_executor_plugin_googlebatch-0.5.1.dist-info/licenses/NOTICE
snakemake_executor_plugin_googlebatch-0.5.1.dist-info/RECORD
