Metadata-Version: 2.4
Name: snakemake-executor-plugin-googlebatch
Version: 0.5.1
Summary: 
License: MIT
License-File: LICENSE
License-File: NOTICE
Keywords: snakemake,plugin,executor,cloud,google-batch
Author: Vanessa Sochat
Author-email: sochat1@llnl.gov
Requires-Python: >=3.11,<4.0
Classifier: License :: OSI Approved :: MIT License
Classifier: Programming Language :: Python :: 3
Classifier: Programming Language :: Python :: 3.11
Classifier: Programming Language :: Python :: 3.12
Classifier: Programming Language :: Python :: 3.13
Classifier: Programming Language :: Python :: 3.14
Requires-Dist: google-api-core (>=2.12.0,<3.0.0)
Requires-Dist: google-cloud-batch (>=0.17.1,<0.18.0)
Requires-Dist: google-cloud-logging (>=3.11.4,<4.0.0)
Requires-Dist: google-cloud-storage (>=2.12.0,<3.0.0)
Requires-Dist: jinja2 (>=3.1.2,<4.0.0)
Requires-Dist: requests (>=2.31.0,<3.0.0)
Requires-Dist: snakemake-interface-common (>=1.14.0,<2.0.0)
Requires-Dist: snakemake-interface-executor-plugins (>=9.0.0,<10.0.0)
Project-URL: Documentation, https://snakemake.github.io/snakemake-plugin-catalog/plugins/executor/googlebatch.html
Project-URL: Repository, https://github.com/snakemake/snakemake-executor-plugin-googlebatch
